feign_client/__init__.py
feign_client/feignClient.py
djangoFeignClient-0.0.1.dist-info/LICENSE
djangoFeignClient-0.0.1.dist-info/METADATA
djangoFeignClient-0.0.1.dist-info/WHEEL
djangoFeignClient-0.0.1.dist-info/top_level.txt
djangoFeignClient-0.0.1.dist-info/RECORD
